nba_draft_utils/data.py
nba_draft_utils/evaluate.py
nba_draft_utils/features.py
nba_draft_utils/models.py
nba_draft_utils/predict.py
nba_draft_utils/train.py
nba_draft_utils/utils.py
utils/utils.py
nba_draft_utils-0.1.2.dist-info/METADATA
nba_draft_utils-0.1.2.dist-info/WHEEL
nba_draft_utils-0.1.2.dist-info/top_level.txt
nba_draft_utils-0.1.2.dist-info/RECORD
