Metadata-Version: 2.4
Name: nba-draft-utils
Version: 0.1.2
Summary: Utilities for NBA draft probability modeling: data loading, preprocessing, model training, evaluation, and Kaggle submission.
Author: Aditya Kulkarni
License: MIT
Requires-Python: <3.12,>=3.11
Requires-Dist: pandas==2.2.2
Requires-Dist: scikit-learn==1.5.1
Requires-Dist: lightgbm==4.4.0
Requires-Dist: xgboost==2.1.0
Requires-Dist: joblib==1.4.2
Requires-Dist: matplotlib>=3.8
Requires-Dist: numpy>=1.26
Requires-Dist: pytest>=8.0
